__init__.py
yt_pld.py
yt_pld-0.0.15.dist-info/METADATA
yt_pld-0.0.15.dist-info/WHEEL
yt_pld-0.0.15.dist-info/top_level.txt
yt_pld-0.0.15.dist-info/RECORD
