Metadata-Version: 2.1
Name: yt_pld
Version: 0.0.15
Summary: Uploading videos to YouTube
Author-email: David <david2002belozerov@mail.ru>
Requires-Python: >=3.8
Requires-Dist: selenium ==4.16.0
